bharel_pastebinapi/__init__.py
bharel_pastebinapi-0.1.0.dist-info/METADATA
bharel_pastebinapi-0.1.0.dist-info/RECORD
bharel_pastebinapi-0.1.0.dist-info/WHEEL
bharel_pastebinapi-0.1.0.dist-info/top_level.txt
